LICENSE.md
README.md
setup.cfg
setup.py
rds_framework/__init__.py
rds_framework.egg-info/PKG-INFO
rds_framework.egg-info/SOURCES.txt
rds_framework.egg-info/dependency_links.txt
rds_framework.egg-info/requires.txt
rds_framework.egg-info/top_level.txt
rds_framework/cache/__init__.py
rds_framework/cache/base.py
rds_framework/cache/nocache.py
rds_framework/cache/search_engine.py
rds_framework/config/__init__.py
rds_framework/helpers/__init__.py
rds_framework/helpers/cnes.py
rds_framework/helpers/http_client.py
rds_framework/searchengine/__init__.py